Workbook

Sheet Tracker
A1: NDMA — AI-Integrated Digital Twin Command Dashboard · Project Tracker
A2: Source: NDMA_Digital_Twin_Proposal.pdf · Phase 1 = one pilot district, riverine flood · Phase 2 = landslide, cyclone, more sensor/crowd inputs · Phase 3 = multi-district scale-up · Edit Start, End and Status; Working days recalculates (weekends and the Holidays tab excluded). Dates are planned from dependencies starting 12 Oct 26.
A3: Module | B3: Category | C3: Task | D3: Sub Task | E3: Description | F3: Acceptance criteria / Definition of done | G3: Start | H3: End | I3: Working days | J3: Status | K3: Dependency / Blocker | L3: Comments | M3: Artifacts
A4: A – Programme Setup & Governance | B4: 1. Project Initiation | C4: Solution Proposal | D4: Draft AI-integrated Digital Twin proposal | E4: Write the solution proposal: problem statement, five-layer solution, dashboard features, usage example, data sources, risks and expected impact. | F4: Done when: proposal (PDF + DOCX) is complete and committed to the repo. | G4: 46286 | H4: 46297 | I4: =NETWORKDAYS(G4,H4,Holidays!$A$2:$A$40) -> 10 | J4: Done | M4: NDMA_Digital_Twin_Proposal.pdf; NDMA_Digital_Twin_Proposal (1).docx
D5: Proposal walkthrough and sign-off with NDMA | E5: Present the proposal to NDMA, capture feedback and get written go-ahead for Phase 1. | F5: Done when: NDMA sign-off (email/minutes) received and feedback logged. | G5: 46307 | H5: 46310 | I5: =NETWORKDAYS(G5,H5,Holidays!$A$2:$A$40) -> 4 | J5: Not Started | K5: After: Draft AI-integrated Digital Twin proposal (P0). Needs: NDMA meeting slot for walkthrough.
C6: Scope & Pilot | D6: Select Phase 1 pilot district | E6: Pick one well-mapped, flood-prone district with CWC gauges, good DEM coverage and a willing DEOC (mitigates the terrain-resolution risk). | F6: Done when: pilot district agreed in writing with a scored selection matrix. | G6: 46311 | H6: 46318 | I6: =NETWORKDAYS(G6,H6,Holidays!$A$2:$A$40) -> 5 | J6: Not Started | K6: After: Proposal walkthrough and sign-off with NDMA (P1). Needs: NDMA / State SDMA nomination of candidate districts.
D7: Lock Phase 1 hazard and scope | E7: Phase 1 = riverine flood in the pilot district. Landslide, cyclone and wider sensor/crowd inputs move to Phase 2; multi-district scale-up is Phase 3. | F7: Done when: in/out-of-scope list signed off by NDMA. | G7: 46321 | H7: 46323 | I7: =NETWORKDAYS(G7,H7,Holidays!$A$2:$A$40) -> 3 | J7: Not Started | K7: After: Select Phase 1 pilot district (P2).
D8: User roles and operational workflows | E8: Interview NDMA, SEOC, DEOC and NDRF/SDRF users; map how they plan shelters, routes and deployments today. | F8: Done when: personas, current-vs-future workflow maps and a prioritised needs list are documented. | G8: 46311 | H8: 46321 | I8: =NETWORKDAYS(G8,H8,Holidays!$A$2:$A$40) -> 6 | J8: Not Started | K8: After: Proposal walkthrough and sign-off with NDMA (P1).
D9: Success metrics and acceptance bar | E9: Agree measurable targets: flood-extent accuracy (IoU/CSI), forecast lead time, route recompute time, dashboard load time. | F9: Done when: metric targets are agreed with NDMA and referenced by validation tasks. | G9: 46324 | H9: 46329 | I9: =NETWORKDAYS(G9,H9,Holidays!$A$2:$A$40) -> 4 | J9: Not Started | K9: After: Lock Phase 1 hazard and scope (P3); User roles and operational workflows (P4).
B10: 2. Data Agreements & Governance | C10: Data-Sharing Agreements | D10: IMD data-sharing agreement | E10: Formal agreement for rainfall nowcasts, district forecasts and cyclone bulletins (API/FTP access). | F10: Done when: signed agreement and working credentials/endpoint for the pilot district. | G10: 46321 | H10: 46346 | I10: =NETWORKDAYS(G10,H10,Holidays!$A$2:$A$40) -> 20 | J10: Not Started | K10: After: Select Phase 1 pilot district (P2). Needs: IMD nodal officer; NDMA letter of request.
D11: CWC data-sharing agreement | E11: Agreement for real-time river gauge levels and flood forecasts. | F11: Done when: signed agreement and live gauge feed access for pilot basins. | G11: 46321 | H11: 46346 | I11: =NETWORKDAYS(G11,H11,Holidays!$A$2:$A$40) -> 20 | J11: Not Started | K11: After: Select Phase 1 pilot district (P2). Needs: CWC nodal officer; NDMA letter of request.
D12: ISRO / NRSC satellite data access | E12: Access to optical and SAR imagery and flood maps (Bhuvan / NDEM) for the pilot district. | F12: Done when: imagery access confirmed and a sample scene downloaded. | G12: 46321 | H12: 46353 | I12: =NETWORKDAYS(G12,H12,Holidays!$A$2:$A$40) -> 25 | J12: Not Started | K12: After: Select Phase 1 pilot district (P2). Needs: NRSC approval via NDMA.
D13: Survey of India high-resolution DEM licence | E13: Licence for high-resolution elevation data — the base terrain of the 3D twin. | F13: Done when: licence signed and DEM tiles for the pilot district received. | G13: 46321 | H13: 46346 | I13: =NETWORKDAYS(G13,H13,Holidays!$A$2:$A$40) -> 20 | J13: Not Started | K13: After: Select Phase 1 pilot district (P2). Needs: SoI licence approval.
D14: Census / LGD data access | E14: Population, household and administrative boundary data for impact and shelter sizing. | F14: Done when: ward/village-level population and LGD boundaries for the pilot district are available. | G14: 46321 | H14: 46332 | I14: =NETWORKDAYS(G14,H14,Holidays!$A$2:$A$40) -> 10 | J14: Not Started | K14: After: Select Phase 1 pilot district (P2).
D15: Google Maps Platform licence and billing | E15: Enable Roads, Places and Traffic APIs with a government billing account and usage caps. | F15: Done when: API keys issued with quotas and a cost estimate approved. | G15: 46311 | H15: 46323 | I15: =NETWORKDAYS(G15,H15,Holidays!$A$2:$A$40) -> 8 | J15: Not Started | K15: After: Proposal walkthrough and sign-off with NDMA (P1). Needs: budget approval for API usage.
D16: Commercial high-resolution imagery procurement | E16: Procure fine-resolution imagery for the pilot district to sharpen terrain and infrastructure detail. | F16: Done when: purchase order issued and imagery delivered. | G16: 46321 | H16: 46360 | I16: =NETWORKDAYS(G16,H16,Holidays!$A$2:$A$40) -> 30 | J16: Not Started | K16: After: Select Phase 1 pilot district (P2). Needs: procurement approval (GeM). | L16: Pilot district only in Phase 1.
C17: Privacy & Data Governance | D17: Data governance and privacy policy | E17: Policy covering citizen location/photo data and social media signals under the DPDP Act 2023: purpose limitation, minimisation, retention, access. | F17: Done when: policy approved by NDMA legal and published internally. | G17: 46311 | H17: 46332 | I17: =NETWORKDAYS(G17,H17,Holidays!$A$2:$A$40) -> 15 | J17: Not Started | K17: After: Proposal walkthrough and sign-off with NDMA (P1). Needs: NDMA legal review. | L17: Runs alongside the technical build (proposal risk: data privacy & consent).
D18: Data classification and retention rules | E18: Classify each data source (public / restricted / personal) and set retention periods. | F18: Done when: every ingested source has a class and retention rule applied in the pipeline config. | G18: 46335 | H18: 46339 | I18: =NETWORKDAYS(G18,H18,Holidays!$A$2:$A$40) -> 5 | J18: Not Started | K18: After: Data governance and privacy policy (G1).
D19: Consent flow for citizen ground reports | E19: Consent text and opt-in flow for WhatsApp / SACHET reports (photo + location). | F19: Done when: consent text approved and recorded with every citizen report. | G19: 46335 | H19: 46339 | I19: =NETWORKDAYS(G19,H19,Holidays!$A$2:$A$40) -> 5 | J19: Not Started | K19: After: Data governance and privacy policy (G1).
A20: B – Unified Data Ingestion (Layer 1) | B20: 3. Ingestion Foundation | C20: Common Data Model | D20: Canonical schema for all feeds | E20: One schema for every source: timestamp (UTC + IST), geometry, source, unit, confidence and raw-payload reference. | F20: Done when: schema documented and validated against samples from every Phase 1 source. | G20: 46324 | H20: 46335 | I20: =NETWORKDAYS(G20,H20,Holidays!$A$2:$A$40) -> 8 | J20: Not Started | K20: After: Lock Phase 1 hazard and scope (P3).
C21: Ingestion Framework | D21: Connector framework and scheduler | E21: Reusable connector framework with scheduling, retries, back-fill and idempotent loads so feeds stay fresh without manual effort. | F21: Done when: scheduled runs complete, resume after interruption and never run twice at once. | G21: 46336 | H21: 46349 | I21: =NETWORKDAYS(G21,H21,Holidays!$A$2:$A$40) -> 10 | J21: Not Started | K21: After: Canonical schema for all feeds (I1); Dev / test / prod environments as code (H1).
D22: Spatial data store (PostGIS + object storage) | E22: Store vector layers, time-series and rasters/imagery in one spatially indexed store. | F22: Done when: store is provisioned in dev/test with spatial indexes and backup. | G22: 46336 | H22: 46345 | I22: =NETWORKDAYS(G22,H22,Holidays!$A$2:$A$40) -> 8 | J22: Not Started | K22: After: Canonical schema for all feeds (I1); Dev / test / prod environments as code (H1).
D23: Pipeline status view (last run, errors, owner) | E23: Simple view showing, per source, when it last succeeded, what failed and who owns it. | F23: Done when: operations can spot a stale/failed feed without engineering help. | G23: 46350 | H23: 46356 | I23: =NETWORKDAYS(G23,H23,Holidays!$A$2:$A$40) -> 5 | J23: Not Started | K23: After: Connector framework and scheduler (I2).
B24: 4. Agency Feeds | C24: IMD | D24: IMD connector (rainfall, forecasts, cyclone bulletins) | E24: Pull nowcasts, district rainfall forecasts and bulletins into the canonical schema. | F24: Done when: IMD data for the pilot district lands every cycle with < 1 cycle lag. | G24: 46350 | H24: 46359 | I24: =NETWORKDAYS(G24,H24,Holidays!$A$2:$A$40) -> 8 | J24: Not Started | K24: After: Connector framework and scheduler (I2); IMD data-sharing agreement (D1).
C25: CWC | D25: CWC connector (gauge levels, flood forecasts) | E25: Pull river gauge levels, danger/warning marks and flood forecasts for the pilot basins. | F25: Done when: all pilot-basin gauges update on schedule with danger marks attached. | G25: 46350 | H25: 46359 | I25: =NETWORKDAYS(G25,H25,Holidays!$A$2:$A$40) -> 8 | J25: Not Started | K25: After: Connector framework and scheduler (I2); CWC data-sharing agreement (D2).
C26: ISRO / NRSC | D26: Satellite imagery connector (optical + SAR) | E26: Ingest optical and SAR scenes and NRSC flood-extent products for change detection. | F26: Done when: new scenes for the pilot district are catalogued automatically. | G26: 46356 | H26: 46367 | I26: =NETWORKDAYS(G26,H26,Holidays!$A$2:$A$40) -> 10 | J26: Not Started | K26: After: Connector framework and scheduler (I2); ISRO / NRSC satellite data access (D3).
C27: Open Satellite | D27: Copernicus Sentinel-1/2 and Landsat connector | E27: Open imagery for flood-extent and land-cover validation (no agreement needed). | F27: Done when: scenes over the pilot district are searchable by date and cloud cover. | G27: 46350 | H27: 46359 | I27: =NETWORKDAYS(G27,H27,Holidays!$A$2:$A$40) -> 8 | J27: Not Started | K27: After: Connector framework and scheduler (I2).
B28: 5. Static & Reference Layers | C28: Terrain | D28: Ingest and tile SoI DEM | E28: Clean, reproject and tile the DEM; fill voids from open DEMs where needed. | F28: Done when: seamless DEM for the pilot district is served as tiles with void report. | G28: 46349 | H28: 46356 | I28: =NETWORKDAYS(G28,H28,Holidays!$A$2:$A$40) -> 6 | J28: Not Started | K28: After: Spatial data store (PostGIS + object storage) (I3); Survey of India high-resolution DEM licence (D4).
C29: Population & Boundaries | D29: Census / LGD population and boundaries | E29: Load ward/village boundaries and population, households and age bands. | F29: Done when: every zone in the pilot district has population and household counts. | G29: 46346 | H29: 46353 | I29: =NETWORKDAYS(G29,H29,Holidays!$A$2:$A$40) -> 6 | J29: Not Started | K29: After: Spatial data store (PostGIS + object storage) (I3); Census / LGD data access (D5).
C30: Infrastructure | D30: Roads, bridges and critical facilities layer | E30: Build roads, bridges, hospitals, schools and govt buildings from OSM + Google Places/Roads. | F30: Done when: routable road network and facility layer cover the pilot district. | G30: 46346 | H30: 46357 | I30: =NETWORKDAYS(G30,H30,Holidays!$A$2:$A$40) -> 8 | J30: Not Started | K30: After: Spatial data store (PostGIS + object storage) (I3); Google Maps Platform licence and billing (D6).
C31: History | D31: Historical disaster records | E31: Collect past flood events: dates, gauge peaks, mapped extents, damage and relief records. | F31: Done when: at least 5 past flood events are catalogued with extents for backtesting. | G31: 46346 | H31: 46359 | I31: =NETWORKDAYS(G31,H31,Holidays!$A$2:$A$40) -> 10 | J31: Not Started | K31: After: Spatial data store (PostGIS + object storage) (I3). | L31: Used to calibrate and backtest every model.
C32: Resources | D32: IDRN resource inventory import | E32: Import India Disaster Resource Network equipment and team inventory for the pilot state. | F32: Done when: IDRN inventory is queryable by location and resource type. | G32: 46346 | H32: 46352 | I32: =NETWORKDAYS(G32,H32,Holidays!$A$2:$A$40) -> 5 | J32: Not Started | K32: After: Spatial data store (PostGIS + object storage) (I3). Needs: IDRN data access via NDMA.
B33: 6. Sensor & Crowdsourced Feeds | C33: Hardware Sensors | D33: River / rain gauge sensor telemetry (pilot) | E33: Ingest telemetry from pilot river-level and rainfall gauges (MQTT/HTTP). | F33: Done when: pilot sensors stream into the store with device health status. | G33: 46350 | H33: 46363 | I33: =NETWORKDAYS(G33,H33,Holidays!$A$2:$A$40) -> 10 | J33: Not Started | K33: After: Connector framework and scheduler (I2). Needs: sensor vendor / state agency feed access.
C34: Ground Reporting | D34: WhatsApp ground-reporting bot | E34: Structured bot for field staff and citizens to send photo + location + short description. | F34: Done when: reports arrive geotagged with consent recorded and reach the ingestion layer. | G34: 46350 | H34: 46365 | I34: =NETWORKDAYS(G34,H34,Holidays!$A$2:$A$40) -> 12 | J34: Not Started | K34: After: Connector framework and scheduler (I2); Consent flow for citizen ground reports (G3). Needs: WhatsApp Business API account.
D35: Report verification and trust score | E35: De-duplicate, geo-check and score reports (image checks, reporter history, agreement with sensors) before they are trusted. | F35: Done when: every report carries a trust score and low-trust reports are held for review. | G35: 46366 | H35: 46379 | I35: =NETWORKDAYS(G35,H35,Holidays!$A$2:$A$40) -> 10 | J35: Not Started | K35: After: WhatsApp ground-reporting bot (I17). | L35: Mitigation for crowdsourced misinformation risk.
B36: 7. Data Quality | C36: Normalisation | D36: Units, CRS and time-zone normalisation | E36: Convert all feeds to common units, one CRS and UTC/IST timestamps. | F36: Done when: no unit/CRS mismatches across Phase 1 sources in the QA report. | G36: 46360 | H36: 46366 | I36: =NETWORKDAYS(G36,H36,Holidays!$A$2:$A$40) -> 5 | J36: Not Started | K36: After: IMD connector (rainfall, forecasts, cyclone bulletins) (I5); CWC connector (gauge levels, flood forecasts) (I6).
C37: Quality Rules | D37: Staleness, gap and outlier rules with alerts | E37: Rules that flag stale feeds, missing values and impossible readings; alert the data owner. | F37: Done when: rules are documented, applied and alerts fire in test. | G37: 46367 | H37: 46374 | I37: =NETWORKDAYS(G37,H37,Holidays!$A$2:$A$40) -> 6 | J37: Not Started | K37: After: Units, CRS and time-zone normalisation (I21).
A38: C – AI/ML Prediction Engine (Layer 2) | B38: 8. EDA & Feature Prep | C38: EDA | D38: EDA on historical floods, rainfall and gauges | E38: Study rainfall–gauge lag, upstream/downstream relationships and past extents in the pilot basin. | F38: Done when: findings and modelling decisions are documented in a notebook. | G38: 46360 | H38: 46371 | I38: =NETWORKDAYS(G38,H38,Holidays!$A$2:$A$40) -> 8 | J38: Not Started | K38: After: Historical disaster records (I12); CWC connector (gauge levels, flood forecasts) (I6); IMD connector (rainfall, forecasts, cyclone bulletins) (I5).
C39: Features | D39: Feature store (rainfall accumulations, upstream levels, soil, land cover) | E39: Reusable, versioned features for all flood models. | F39: Done when: features are reproducible from raw data with one command. | G39: 46377 | H39: 46387 | I39: =NETWORKDAYS(G39,H39,Holidays!$A$2:$A$40) -> 8 | J39: Not Started | K39: After: EDA on historical floods, rainfall and gauges (M1); Staleness, gap and outlier rules with alerts (I22).
B40: 9. Flood Forecasting | C40: Hydraulic Model | D40: Hydraulic/hydrological model set-up on DEM | E40: Set up a physics model (e.g. HEC-RAS 2D / LISFLOOD-FP) for the pilot basin and calibrate on past events. | F40: Done when: model reproduces at least 3 historical extents within the agreed accuracy bar. | G40: 46372 | H40: 46393 | I40: =NETWORKDAYS(G40,H40,Holidays!$A$2:$A$40) -> 15 | J40: Not Started | K40: After: Ingest and tile SoI DEM (I9); EDA on historical floods, rainfall and gauges (M1).
C41: ML Forecaster | D41: Gauge-level forecaster (6/12/24/48 h) | E41: ML model (e.g. LSTM / gradient boosting) forecasting gauge levels from rainfall and upstream levels. | F41: Done when: beats CWC persistence baseline on held-out seasons. | G41: 46388 | H41: 46408 | I41: =NETWORKDAYS(G41,H41,Holidays!$A$2:$A$40) -> 15 | J41: Not Started | K41: After: Feature store (rainfall accumulations, upstream levels, soil, land cover) (M2).
C42: Flood Extent | D42: Flood-extent prediction (hydraulic + ML surrogate) | E42: Fast surrogate of the hydraulic model driven by forecast levels to produce extents in minutes. | F42: Done when: surrogate extents match the full model within the agreed tolerance and run in < 5 min. | G42: 46409 | H42: 46430 | I42: =NETWORKDAYS(G42,H42,Holidays!$A$2:$A$40) -> 15 | J42: Not Started | K42: After: Hydraulic/hydrological model set-up on DEM (M3); Gauge-level forecaster (6/12/24/48 h) (M4).
C43: Fusion | D43: Fuse IMD, CWC and ISRO signals into one forecast | E43: Combine agency forecasts, sensor data and satellite-observed extents into one localised forecast. | F43: Done when: one fused forecast is produced per cycle with source contributions logged. | G43: 46433 | H43: 46444 | I43: =NETWORKDAYS(G43,H43,Holidays!$A$2:$A$40) -> 10 | J43: Not Started | K43: After: Flood-extent prediction (hydraulic + ML surrogate) (M5); Satellite imagery connector (optical + SAR) (I7); River / rain gauge sensor telemetry (pilot) (I14).
B44: 10. Risk Scoring | C44: Zone Risk | D44: Per-zone risk score | E44: Continuously updated risk score per zone (ward / hex grid) combining hazard and exposure. | F44: Done when: every zone has a score refreshed each forecast cycle. | G44: 46447 | H44: 46456 | I44: =NETWORKDAYS(G44,H44,Holidays!$A$2:$A$40) -> 8 | J44: Not Started | K44: After: Fuse IMD, CWC and ISRO signals into one forecast (M6); Census / LGD population and boundaries (I10).
C45: Time-Boxed Forecast | D45: Hour-by-hour hazard extents | E45: Time-boxed forecasts (e.g. extent X by hour 18, Y by hour 24) instead of static labels. | F45: Done when: hourly extents for the forecast window are published per cycle. | G45: 46457 | H45: 46464 | I45: =NETWORKDAYS(G45,H45,Holidays!$A$2:$A$40) -> 6 | J45: Not Started | K45: After: Per-zone risk score (M7).
C46: Uncertainty | D46: Confidence bands for extents and scores | E46: Show likely / worst-case extents and a confidence level so operators know how far to trust each forecast. | F46: Done when: every forecast carries a confidence band and calibration is checked. | G46: 46465 | H46: 46475 | I46: =NETWORKDAYS(G46,H46,Holidays!$A$2:$A$40) -> 6 | J46: Not Started | K46: After: Hour-by-hour hazard extents (M8).
C47: Thresholds | D47: Critical-threshold and alert rules | E47: Rules that raise alerts and trigger pre-positioning when a zone crosses a critical score. | F47: Done when: thresholds are agreed with NDMA and alerts fire correctly in replay. | G47: 46476 | H47: 46479 | I47: =NETWORKDAYS(G47,H47,Holidays!$A$2:$A$40) -> 4 | J47: Not Started | K47: After: Confidence bands for extents and scores (M9); Success metrics and acceptance bar (P5).
B48: 11. Model Validation | C48: Backtesting | D48: Backtest against historical events | E48: Replay past floods end to end and compare predicted vs observed extents, timings and gauges. | F48: Done when: backtest report meets the agreed acceptance bar for all catalogued events. | G48: 46465 | H48: 46479 | I48: =NETWORKDAYS(G48,H48,Holidays!$A$2:$A$40) -> 10 | J48: Not Started | K48: After: Hour-by-hour hazard extents (M8); Historical disaster records (I12). | L48: Mitigation for model-trust risk.
C49: Reporting | D49: Model card and accuracy report | E49: Plain-language model card: data, method, accuracy by zone, known weaknesses. | F49: Done when: reviewed and accepted by NDMA technical committee. | G49: 46482 | H49: 46485 | I49: =NETWORKDAYS(G49,H49,Holidays!$A$2:$A$40) -> 4 | J49: Not Started | K49: After: Backtest against historical events (M11).
A50: D – Digital Twin Simulation (Layer 3) | B50: 12. 3D Base Twin | C50: Engine | D50: 3D engine selection and spike | E50: Compare CesiumJS, deck.gl and similar for terrain, 3D tiles, time animation and offline support. | F50: Done when: engine chosen with a working spike on pilot terrain. | G50: 46324 | H50: 46330 | I50: =NETWORKDAYS(G50,H50,Holidays!$A$2:$A$40) -> 5 | J50: Not Started | K50: After: Lock Phase 1 hazard and scope (P3).
C51: Terrain | D51: Terrain mesh from DEM (3D tiles) | E51: Convert the DEM into streamable 3D terrain tiles. | F51: Done when: pilot district terrain loads smoothly in the browser. | G51: 46357 | H51: 46366 | I51: =NETWORKDAYS(G51,H51,Holidays!$A$2:$A$40) -> 8 | J51: Not Started | K51: After: 3D engine selection and spike (T1); Ingest and tile SoI DEM (I9).
C52: Infrastructure | D52: Buildings and infrastructure 3D layer | E52: Extrude buildings and add roads, bridges and critical facilities to the twin. | F52: Done when: critical facilities and road network are visible and selectable. | G52: 46367 | H52: 46380 | I52: =NETWORKDAYS(G52,H52,Holidays!$A$2:$A$40) -> 10 | J52: Not Started | K52: After: Terrain mesh from DEM (3D tiles) (T2); Roads, bridges and critical facilities layer (I11).
C53: Imagery | D53: Satellite imagery drape | E53: Drape latest optical imagery (open + commercial) over terrain. | F53: Done when: imagery layer can be switched by date. | G53: 46367 | H53: 46373 | I53: =NETWORKDAYS(G53,H53,Holidays!$A$2:$A$40) -> 5 | J53: Not Started | K53: After: Terrain mesh from DEM (3D tiles) (T2); Copernicus Sentinel-1/2 and Landsat connector (I8).
B54: 13. Hazard Simulation | C54: Animation | D54: Animated flood spread over forecast window | E54: Render forecast extents and depths as an animated layer on the twin. | F54: Done when: the twin animates predicted spread hour by hour for any forecast cycle. | G54: 46465 | H54: 46479 | I54: =NETWORKDAYS(G54,H54,Holidays!$A$2:$A$40) -> 10 | J54: Not Started | K54: After: Buildings and infrastructure 3D layer (T3); Hour-by-hour hazard extents (M8).
C55: Timeline | D55: Timeline scrubber (rewind / fast-forward) | E55: Rotate, zoom and scrub through the forecast timeline. | F55: Done when: operators can jump to any forecast hour in < 2 s. | G55: 46482 | H55: 46489 | I55: =NETWORKDAYS(G55,H55,Holidays!$A$2:$A$40) -> 6 | J55: Not Started | K55: After: Animated flood spread over forecast window (T5).
C56: Impact View | D56: Cut-off roads and threatened neighbourhoods | E56: Highlight roads predicted to flood and neighbourhoods at risk, readable by non-technical users. | F56: Done when: cut-off roads and threatened areas are highlighted per forecast hour. | G56: 46482 | H56: 46489 | I56: =NETWORKDAYS(G56,H56,Holidays!$A$2:$A$40) -> 6 | J56: Not Started | K56: After: Animated flood spread over forecast window (T5); Roads, bridges and critical facilities layer (I11).
C57: Performance | D57: Performance on SEOC / district hardware | E57: Optimise tiles and rendering for typical control-room machines and bandwidth. | F57: Done when: first load < 5 s and smooth playback on agreed reference hardware. | G57: 46490 | H57: 46496 | I57: =NETWORKDAYS(G57,H57,Holidays!$A$2:$A$40) -> 5 | J57: Not Started | K57: After: Timeline scrubber (rewind / fast-forward) (T6).
B58: 14. Shadow Mode | C58: Replay | D58: Replay historical events in the twin | E58: Run the twin against past floods to validate behaviour before live use. | F58: Done when: any catalogued historical event can be replayed end to end. | G58: 46490 | H58: 46499 | I58: =NETWORKDAYS(G58,H58,Holidays!$A$2:$A$40) -> 8 | J58: Not Started | K58: After: Timeline scrubber (rewind / fast-forward) (T6); Backtest against historical events (M11).
C59: Comparison | D59: Predicted vs observed side-by-side | E59: Overlay observed extents (satellite) on predicted extents with an error summary. | F59: Done when: side-by-side view and error summary are available for every replayed event. | G59: 46500 | H59: 46507 | I59: =NETWORKDAYS(G59,H59,Holidays!$A$2:$A$40) -> 6 | J59: Not Started | K59: After: Replay historical events in the twin (T9).
A60: E – Planning & Decision Support (Layer 4) | B60: 15. Impact & Affected-Area Analysis | C60: Affected Population | D60: Affected population and households per zone | E60: Overlay Census/LGD population on hazard extents to estimate people and households affected. | F60: Done when: per-zone affected counts are produced for every forecast hour. | G60: 46457 | H60: 46468 | I60: =NETWORKDAYS(G60,H60,Holidays!$A$2:$A$40) -> 8 | J60: Not Started | K60: After: Per-zone risk score (M7); Census / LGD population and boundaries (I10).
C61: Infrastructure | D61: Critical infrastructure exposure | E61: List hospitals, schools, bridges, substations etc. inside predicted extents. | F61: Done when: exposed assets are listed per zone and hour. | G61: 46469 | H61: 46477 | I61: =NETWORKDAYS(G61,H61,Holidays!$A$2:$A$40) -> 6 | J61: Not Started | K61: After: Affected population and households per zone (E1); Roads, bridges and critical facilities layer (I11).
C62: Projections | D62: Time-boxed impact projections | E62: Impact numbers by hour (e.g. 'X households by hour 18, Y by hour 24'). | F62: Done when: projections refresh automatically with each forecast cycle. | G62: 46469 | H62: 46476 | I62: =NETWORKDAYS(G62,H62,Holidays!$A$2:$A$40) -> 5 | J62: Not Started | K62: After: Affected population and households per zone (E1); Hour-by-hour hazard extents (M8).
C63: Vulnerability | D63: Vulnerable-pocket flagging | E63: Flag high-risk zones with vulnerable groups (e.g. elderly) lacking nearby heavy-equipment teams via IDRN. | F63: Done when: vulnerable pockets are flagged with the reason shown. | G63: 46478 | H63: 46489 | I63: =NETWORKDAYS(G63,H63,Holidays!$A$2:$A$40) -> 8 | J63: Not Started | K63: After: Critical infrastructure exposure (E2); IDRN resource inventory import (I13).
B64: 16. Shelter & Safe-House Planning | C64: Shelter Candidates | D64: Candidate shelters outside the hazard zone | E64: Identify schools, community halls and govt buildings (Places/POI + local lists) outside predicted extents. | F64: Done when: candidate list updates with each forecast and excludes sites inside the extent. | G64: 46469 | H64: 46479 | I64: =NETWORKDAYS(G64,H64,Holidays!$A$2:$A$40) -> 8 | J64: Not Started | K64: After: Affected population and households per zone (E1); Roads, bridges and critical facilities layer (I11).
D65: Shelter suitability scoring | E65: Score candidates on capacity, access route safety, distance and facilities. | F65: Done when: ranked shortlist is produced per affected zone. | G65: 46482 | H65: 46489 | I65: =NETWORKDAYS(G65,H65,Holidays!$A$2:$A$40) -> 6 | J65: Not Started | K65: After: Candidate shelters outside the hazard zone (E5).
C66: Capacity | D66: Live shelter capacity tracking | E66: Track occupancy so operators see which shelters are filling up. | F66: Done when: occupancy can be updated by field staff and shows on the dashboard. | G66: 46490 | H66: 46499 | I66: =NETWORKDAYS(G66,H66,Holidays!$A$2:$A$40) -> 8 | J66: Not Started | K66: After: Shelter suitability scoring (E6).
D67: Shelter demand vs capacity gap | E67: Compare projected displaced population with available capacity by zone and hour. | F67: Done when: gaps are flagged with suggested extra sites. | G67: 46500 | H67: 46506 | I67: =NETWORKDAYS(G67,H67,Holidays!$A$2:$A$40) -> 5 | J67: Not Started | K67: After: Live shelter capacity tracking (E7); Time-boxed impact projections (E3).
B68: 17. Evacuation Route Planning | C68: Road Graph | D68: Routable road graph with predicted closures | E68: Mark road segments predicted to flood or close for each forecast hour. | F68: Done when: graph reflects predicted closures per forecast hour. | G68: 46465 | H68: 46479 | I68: =NETWORKDAYS(G68,H68,Holidays!$A$2:$A$40) -> 10 | J68: Not Started | K68: After: Roads, bridges and critical facilities layer (I11); Hour-by-hour hazard extents (M8).
C69: Routing | D69: Safe evacuation route computation | E69: Compute evacuation routes from affected zones to shelters avoiding predicted closures. | F69: Done when: every affected zone has a safe route to its assigned shelter or is flagged as cut off. | G69: 46490 | H69: 46499 | I69: =NETWORKDAYS(G69,H69,Holidays!$A$2:$A$40) -> 8 | J69: Not Started | K69: After: Routable road graph with predicted closures (E9); Shelter suitability scoring (E6).
D70: Relief-vehicle routing with live traffic | E70: Routes for relief vehicles using Google Roads/Traffic plus predicted hazard. | F70: Done when: relief routes include live traffic and avoid predicted closures. | G70: 46500 | H70: 46507 | I70: =NETWORKDAYS(G70,H70,Holidays!$A$2:$A$40) -> 6 | J70: Not Started | K70: After: Safe evacuation route computation (E10); Google Maps Platform licence and billing (D6).
D71: Automatic recompute on forecast update | E71: Recompute routes whenever the forecast changes so plans are always current. | F71: Done when: routes refresh within 5 min of a new forecast. | G71: 46500 | H71: 46506 | I71: =NETWORKDAYS(G71,H71,Holidays!$A$2:$A$40) -> 5 | J71: Not Started | K71: After: Safe evacuation route computation (E10).
C72: De-confliction | D72: Citizen vs NDRF route conflict detection | E72: Flag where citizen evacuation routes and NDRF relief routes collide. | F72: Done when: conflicts are flagged with suggested alternatives. | G72: 46510 | H72: 46517 | I72: =NETWORKDAYS(G72,H72,Holidays!$A$2:$A$40) -> 6 | J72: Not Started | K72: After: Relief-vehicle routing with live traffic (E11).
C73: Export | D73: Export route and shelter plans for official channels | E73: Operator-issued export for SACHET / Cell Broadcast. Nothing is sent automatically. | F73: Done when: plans export in the agreed format after operator approval. | G73: 46507 | H73: 46512 | I73: =NETWORKDAYS(G73,H73,Holidays!$A$2:$A$40) -> 4 | J73: Not Started | K73: After: Automatic recompute on forecast update (E12); Shelter demand vs capacity gap (E8). Needs: SACHET / C-DOT message format confirmation.
A74: F – Force Coordination & Control (Layer 5) | B74: 18. Force Tracking | C74: Unit Registry | D74: NDRF / SDRF unit and capability registry | E74: Register units, capabilities, equipment and home bases. | F74: Done when: all units for the pilot state are registered with capabilities. | G74: 46353 | H74: 46359 | I74: =NETWORKDAYS(G74,H74,Holidays!$A$2:$A$40) -> 5 | J74: Not Started | K74: After: IDRN resource inventory import (I13). Needs: NDRF / SDRF unit data.
C75: Live Tracking | D75: GPS / radio tracking integration | E75: Plot responder positions from GPS devices or existing radio tracking. | F75: Done when: live positions update on the map at the agreed interval. | G75: 46360 | H75: 46373 | I75: =NETWORKDAYS(G75,H75,Holidays!$A$2:$A$40) -> 10 | J75: Not Started | K75: After: NDRF / SDRF unit and capability registry (F1). Needs: NDRF tracking feed access.
D76: Forces on the 3D twin | E76: Show unit positions on the hazard simulation. | F76: Done when: units appear on the twin with status and last-seen time. | G76: 46490 | H76: 46496 | I76: =NETWORKDAYS(G76,H76,Holidays!$A$2:$A$40) -> 5 | J76: Not Started | K76: After: GPS / radio tracking integration (F2); Timeline scrubber (rewind / fast-forward) (T6).
B77: 19. Predictive Pre-positioning | C77: Staging | D77: Staging locations outside predicted zone | E77: Choose staging points that remain outside the predicted extent and are reachable. | F77: Done when: staging candidates stay valid across the whole forecast window. | G77: 46482 | H77: 46491 | I77: =NETWORKDAYS(G77,H77,Holidays!$A$2:$A$40) -> 8 | J77: Not Started | K77: After: Critical-threshold and alert rules (M10); Candidate shelters outside the hazard zone (E5).
C78: Deployment Plans | D78: Auto-generated deployment plan | E78: When a zone crosses the critical threshold, recommend which units move, where and by when. | F78: Done when: plans are generated within 5 min of a threshold crossing. | G78: 46492 | H78: 46505 | I78: =NETWORKDAYS(G78,H78,Holidays!$A$2:$A$40) -> 10 | J78: Not Started | K78: After: Staging locations outside predicted zone (F4); NDRF / SDRF unit and capability registry (F1).
D79: ETA estimation | E79: Estimated arrival times using hazard-aware routing. | F79: Done when: every plan shows ETAs that account for predicted closures. | G79: 46510 | H79: 46514 | I79: =NETWORKDAYS(G79,H79,Holidays!$A$2:$A$40) -> 5 | J79: Not Started | K79: After: Auto-generated deployment plan (F5); Relief-vehicle routing with live traffic (E11).
C80: Human in the Loop | D80: Commander approval workflow | E80: Commanders accept, edit or reject recommendations; all decisions are logged. | F80: Done when: no recommendation is actioned without approval and every decision is audited. | G80: 46506 | H80: 46512 | I80: =NETWORKDAYS(G80,H80,Holidays!$A$2:$A$40) -> 5 | J80: Not Started | K80: After: Auto-generated deployment plan (F5).
B81: 20. Unified Command View | C81: SEOC Screen | D81: Unified SEOC command screen | E81: One screen with hazard zones, force deployments and ETAs, replacing radio check-ins. | F81: Done when: SEOC staff can run a full scenario from this one screen. | G81: 46517 | H81: 46526 | I81: =NETWORKDAYS(G81,H81,Holidays!$A$2:$A$40) -> 8 | J81: Not Started | K81: After: Forces on the 3D twin (F3); ETA estimation (F6); Commander approval workflow (F7); Shelter demand vs capacity gap (E8).
A82: G – Command Dashboard & Feedback Loop | B82: 21. Dashboard UX | C82: UX Research | D82: Wireframes from user workflows | E82: Low-fidelity wireframes of all panels based on the workflow study. | F82: Done when: wireframes are reviewed with NDMA and SEOC users. | G82: 46322 | H82: 46335 | I82: =NETWORKDAYS(G82,H82,Holidays!$A$2:$A$40) -> 10 | J82: Not Started | K82: After: User roles and operational workflows (P4).
C83: Design | D83: Design system and high-fidelity mockups | E83: Visual design, colour scales for risk, accessibility and control-room (large screen) layouts. | F83: Done when: mockups approved by NDMA. | G83: 46336 | H83: 46345 | I83: =NETWORKDAYS(G83,H83,Holidays!$A$2:$A$40) -> 8 | J83: Not Started | K83: After: Wireframes from user workflows (U1).
B84: 22. Dashboard Build | C84: Shell | D84: Dashboard shell (login, layout, layer toggles) | E84: Base app: SSO login, layout, map/twin container and layer controls. | F84: Done when: shell is deployed in test with SSO. | G84: 46346 | H84: 46359 | I84: =NETWORKDAYS(G84,H84,Holidays!$A$2:$A$40) -> 10 | J84: Not Started | K84: After: Design system and high-fidelity mockups (U2); 3D engine selection and spike (T1); SSO, role-based access and audit logs (H3).
D85: Role-based views (NDMA, SEOC, DEOC, NDRF) | E85: Each role sees the panels and areas relevant to it. | F85: Done when: each role sees only its permitted views and data. | G85: 46360 | H85: 46367 | I85: =NETWORKDAYS(G85,H85,Holidays!$A$2:$A$40) -> 6 | J85: Not Started | K85: After: Dashboard shell (login, layout, layer toggles) (U3).
C86: Panels | D86: Risk and alerts panel | E86: Per-zone risk scores, threshold alerts and confidence. | F86: Done when: alerts appear within one forecast cycle of a threshold crossing. | G86: 46482 | H86: 46489 | I86: =NETWORKDAYS(G86,H86,Holidays!$A$2:$A$40) -> 6 | J86: Not Started | K86: After: Dashboard shell (login, layout, layer toggles) (U3); Critical-threshold and alert rules (M10).
D87: Impact panel | E87: Affected population, households, infrastructure and vulnerable pockets. | F87: Done when: panel matches the impact analysis outputs. | G87: 46490 | H87: 46496 | I87: =NETWORKDAYS(G87,H87,Holidays!$A$2:$A$40) -> 5 | J87: Not Started | K87: After: Dashboard shell (login, layout, layer toggles) (U3); Vulnerable-pocket flagging (E4).
D88: Shelter panel | E88: Shelter recommendations, live capacity and gaps. | F88: Done when: operators can review, edit and lock a shelter plan. | G88: 46507 | H88: 46513 | I88: =NETWORKDAYS(G88,H88,Holidays!$A$2:$A$40) -> 5 | J88: Not Started | K88: After: Dashboard shell (login, layout, layer toggles) (U3); Shelter demand vs capacity gap (E8).
D89: Route planning workspace | E89: Evacuation and relief routes with conflicts and export. | F89: Done when: operators can generate, compare and export route plans. | G89: 46518 | H89: 46525 | I89: =NETWORKDAYS(G89,H89,Holidays!$A$2:$A$40) -> 6 | J89: Not Started | K89: After: Dashboard shell (login, layout, layer toggles) (U3); Citizen vs NDRF route conflict detection (E13); Export route and shelter plans for official channels (E14).
C90: Accessibility | D90: English / Hindi interface | E90: Bilingual labels and reports for district users. | F90: Done when: all labels and exports are available in English and Hindi. | G90: 46370 | H90: 46373 | I90: =NETWORKDAYS(G90,H90,Holidays!$A$2:$A$40) -> 4 | J90: Not Started | K90: After: Role-based views (NDMA, SEOC, DEOC, NDRF) (U4).
D91: Low-bandwidth mode for district EOCs | E91: Lighter 2D fallback and cached tiles for poor connectivity. | F91: Done when: dashboard is usable at the agreed low-bandwidth profile. | G91: 46497 | H91: 46504 | I91: =NETWORKDAYS(G91,H91,Holidays!$A$2:$A$40) -> 6 | J91: Not Started | K91: After: Role-based views (NDMA, SEOC, DEOC, NDRF) (U4); Performance on SEOC / district hardware (T8).
B92: 23. Continuous Feedback | C92: Feedback Loop | D92: Ground reports update the forecast | E92: Verified ground reports adjust the observed state and trigger a re-forecast. | F92: Done when: a verified report changes the next forecast cycle and is traceable. | G92: 46465 | H92: 46477 | I92: =NETWORKDAYS(G92,H92,Holidays!$A$2:$A$40) -> 8 | J92: Not Started | K92: After: Report verification and trust score (I20); Hour-by-hour hazard extents (M8).
D93: Sensor and force updates in near real time | E93: Live sensor and force-position updates refresh forecast, routes and plans. | F93: Done when: dashboard refreshes within the agreed latency after new data. | G93: 46507 | H93: 46518 | I93: =NETWORKDAYS(G93,H93,Holidays!$A$2:$A$40) -> 8 | J93: Not Started | K93: After: Ground reports update the forecast (FB1); GPS / radio tracking integration (F2); Automatic recompute on forecast update (E12).
D94: Operator verification queue for reports | E94: Queue where operators confirm or reject low-trust reports. | F94: Done when: every low-trust report is reviewed or expires with a reason. | G94: 46380 | H94: 46387 | I94: =NETWORKDAYS(G94,H94,Holidays!$A$2:$A$40) -> 5 | J94: Not Started | K94: After: Report verification and trust score (I20); Dashboard shell (login, layout, layer toggles) (U3).
A95: H – Platform, Security & MLOps | B95: 24. Infrastructure | C95: Hosting | D95: Hosting decision (MeghRaj / NIC / GovCloud) | E95: Choose a government-approved cloud with data residency in India. | F95: Done when: hosting is approved in writing and accounts are provisioned. | G95: 46311 | H95: 46318 | I95: =NETWORKDAYS(G95,H95,Holidays!$A$2:$A$40) -> 5 | J95: Not Started | K95: After: Proposal walkthrough and sign-off with NDMA (P1). Needs: NDMA IT approval.
C96: Environments | D96: Dev / test / prod environments as code | E96: Infrastructure-as-code for all environments. | F96: Done when: environments can be rebuilt from code. | G96: 46321 | H96: 46330 | I96: =NETWORKDAYS(G96,H96,Holidays!$A$2:$A$40) -> 8 | J96: Not Started | K96: After: Hosting decision (MeghRaj / NIC / GovCloud) (H0).
C97: Delivery | D97: CI/CD pipeline | E97: Automated tests, builds and deployments. | F97: Done when: every merge deploys to test automatically. | G97: 46331 | H97: 46337 | I97: =NETWORKDAYS(G97,H97,Holidays!$A$2:$A$40) -> 5 | J97: Not Started | K97: After: Dev / test / prod environments as code (H1).
C98: Resilience | D98: Backup and disaster recovery | E98: Backups and a recovery plan — the system must stay up during disasters. | F98: Done when: restore drill succeeds within the agreed RTO/RPO. | G98: 46331 | H98: 46337 | I98: =NETWORKDAYS(G98,H98,Holidays!$A$2:$A$40) -> 5 | J98: Not Started | K98: After: Dev / test / prod environments as code (H1).
B99: 25. Security | C99: Access | D99: SSO, role-based access and audit logs | E99: Single sign-on, role-based permissions and audit trail of every action. | F99: Done when: all actions are attributable to a user in the audit log. | G99: 46331 | H99: 46338 | I99: =NETWORKDAYS(G99,H99,Holidays!$A$2:$A$40) -> 6 | J99: Not Started | K99: After: Dev / test / prod environments as code (H1).
C100: Data Protection | D100: Encryption and secrets management | E100: Encrypt data at rest/in transit; keep keys in a secrets manager. | F100: Done when: no plaintext secrets in code or config; encryption verified. | G100: 46331 | H100: 46336 | I100: =NETWORKDAYS(G100,H100,Holidays!$A$2:$A$40) -> 4 | J100: Not Started | K100: After: Dev / test / prod environments as code (H1).
...

Sheet Summary
A1: Summary by Module
A2: All figures are formulas over the Tracker tab; they update as Status and dates change.
A3: Module | B3: Sub tasks | C3: Done | D3: In Progress | E3: Not Started | F3: Blocked | G3: % Done | H3: Start | I3: End | J3: Working days
A4: A – Programme Setup & Governance | B4: =COUNTA(Tracker!$D$4:$D$19) -> 16 | C4: =COUNTIF(Tracker!$J$4:$J$19,"Done") -> 1 | D4: =COUNTIF(Tracker!$J$4:$J$19,"In Progress") -> 0 | E4: =COUNTIF(Tracker!$J$4:$J$19,"Not Started") -> 15 | F4: =COUNTIF(Tracker!$J$4:$J$19,"Blocked") -> 0 | G4: =IF(B4=0,0,C4/B4) -> 0.0625 | H4: =MIN(Tracker!$G$4:$G$19) -> 46286 | I4: =MAX(Tracker!$H$4:$H$19) -> 46360 | J4: =NETWORKDAYS(H4,I4,Holidays!$A$2:$A$40) -> 54
A5: B – Unified Data Ingestion (Layer 1) | B5: =COUNTA(Tracker!$D$20:$D$37) -> 18 | C5: =COUNTIF(Tracker!$J$20:$J$37,"Done") -> 0 | D5: =COUNTIF(Tracker!$J$20:$J$37,"In Progress") -> 0 | E5: =COUNTIF(Tracker!$J$20:$J$37,"Not Started") -> 18 | F5: =COUNTIF(Tracker!$J$20:$J$37,"Blocked") -> 0 | G5: =IF(B5=0,0,C5/B5) -> 0 | H5: =MIN(Tracker!$G$20:$G$37) -> 46324 | I5: =MAX(Tracker!$H$20:$H$37) -> 46379 | J5: =NETWORKDAYS(H5,I5,Holidays!$A$2:$A$40) -> 40
A6: C – AI/ML Prediction Engine (Layer 2) | B6: =COUNTA(Tracker!$D$38:$D$49) -> 12 | C6: =COUNTIF(Tracker!$J$38:$J$49,"Done") -> 0 | D6: =COUNTIF(Tracker!$J$38:$J$49,"In Progress") -> 0 | E6: =COUNTIF(Tracker!$J$38:$J$49,"Not Started") -> 12 | F6: =COUNTIF(Tracker!$J$38:$J$49,"Blocked") -> 0 | G6: =IF(B6=0,0,C6/B6) -> 0 | H6: =MIN(Tracker!$G$38:$G$49) -> 46360 | I6: =MAX(Tracker!$H$38:$H$49) -> 46485 | J6: =NETWORKDAYS(H6,I6,Holidays!$A$2:$A$40) -> 87
A7: D – Digital Twin Simulation (Layer 3) | B7: =COUNTA(Tracker!$D$50:$D$59) -> 10 | C7: =COUNTIF(Tracker!$J$50:$J$59,"Done") -> 0 | D7: =COUNTIF(Tracker!$J$50:$J$59,"In Progress") -> 0 | E7: =COUNTIF(Tracker!$J$50:$J$59,"Not Started") -> 10 | F7: =COUNTIF(Tracker!$J$50:$J$59,"Blocked") -> 0 | G7: =IF(B7=0,0,C7/B7) -> 0 | H7: =MIN(Tracker!$G$50:$G$59) -> 46324 | I7: =MAX(Tracker!$H$50:$H$59) -> 46507 | J7: =NETWORKDAYS(H7,I7,Holidays!$A$2:$A$40) -> 129
A8: E – Planning & Decision Support (Layer 4) | B8: =COUNTA(Tracker!$D$60:$D$73) -> 14 | C8: =COUNTIF(Tracker!$J$60:$J$73,"Done") -> 0 | D8: =COUNTIF(Tracker!$J$60:$J$73,"In Progress") -> 0 | E8: =COUNTIF(Tracker!$J$60:$J$73,"Not Started") -> 14 | F8: =COUNTIF(Tracker!$J$60:$J$73,"Blocked") -> 0 | G8: =IF(B8=0,0,C8/B8) -> 0 | H8: =MIN(Tracker!$G$60:$G$73) -> 46457 | I8: =MAX(Tracker!$H$60:$H$73) -> 46517 | J8: =NETWORKDAYS(H8,I8,Holidays!$A$2:$A$40) -> 42
A9: F – Force Coordination & Control (Layer 5) | B9: =COUNTA(Tracker!$D$74:$D$81) -> 8 | C9: =COUNTIF(Tracker!$J$74:$J$81,"Done") -> 0 | D9: =COUNTIF(Tracker!$J$74:$J$81,"In Progress") -> 0 | E9: =COUNTIF(Tracker!$J$74:$J$81,"Not Started") -> 8 | F9: =COUNTIF(Tracker!$J$74:$J$81,"Blocked") -> 0 | G9: =IF(B9=0,0,C9/B9) -> 0 | H9: =MIN(Tracker!$G$74:$G$81) -> 46353 | I9: =MAX(Tracker!$H$74:$H$81) -> 46526 | J9: =NETWORKDAYS(H9,I9,Holidays!$A$2:$A$40) -> 121
A10: G – Command Dashboard & Feedback Loop | B10: =COUNTA(Tracker!$D$82:$D$94) -> 13 | C10: =COUNTIF(Tracker!$J$82:$J$94,"Done") -> 0 | D10: =COUNTIF(Tracker!$J$82:$J$94,"In Progress") -> 0 | E10: =COUNTIF(Tracker!$J$82:$J$94,"Not Started") -> 13 | F10: =COUNTIF(Tracker!$J$82:$J$94,"Blocked") -> 0 | G10: =IF(B10=0,0,C10/B10) -> 0 | H10: =MIN(Tracker!$G$82:$G$94) -> 46322 | I10: =MAX(Tracker!$H$82:$H$94) -> 46525 | J10: =NETWORKDAYS(H10,I10,Holidays!$A$2:$A$40) -> 143
A11: H – Platform, Security & MLOps | B11: =COUNTA(Tracker!$D$95:$D$105) -> 11 | C11: =COUNTIF(Tracker!$J$95:$J$105,"Done") -> 0 | D11: =COUNTIF(Tracker!$J$95:$J$105,"In Progress") -> 0 | E11: =COUNTIF(Tracker!$J$95:$J$105,"Not Started") -> 11 | F11: =COUNTIF(Tracker!$J$95:$J$105,"Blocked") -> 0 | G11: =IF(B11=0,0,C11/B11) -> 0 | H11: =MIN(Tracker!$G$95:$G$105) -> 46311 | I11: =MAX(Tracker!$H$95:$H$105) -> 46554 | J11: =NETWORKDAYS(H11,I11,Holidays!$A$2:$A$40) -> 170
A12: I – Pilot, Validation & Rollout | B12: =COUNTA(Tracker!$D$106:$D$119) -> 14 | C12: =COUNTIF(Tracker!$J$106:$J$119,"Done") -> 0 | D12: =COUNTIF(Tracker!$J$106:$J$119,"In Progress") -> 0 | E12: =COUNTIF(Tracker!$J$106:$J$119,"Not Started") -> 14 | F12: =COUNTIF(Tracker!$J$106:$J$119,"Blocked") -> 0 | G12: =IF(B12=0,0,C12/B12) -> 0 | H12: =MIN(Tracker!$G$106:$G$119) -> 46527 | I12: =MAX(Tracker!$H$106:$H$119) -> 46723 | J12: =NETWORKDAYS(H12,I12,Holidays!$A$2:$A$40) -> 141
A13: Total | B13: =SUM(B4:B12) -> 116 | C13: =SUM(C4:C12) -> 1 | D13: =SUM(D4:D12) -> 0 | E13: =SUM(E4:E12) -> 115 | F13: =SUM(F4:F12) -> 0 | G13: =IF(B13=0,0,C13/B13) -> 0.0086206897 | H13: =MIN(H4:H12) -> 46286 | I13: =MAX(I4:I12) -> 46723 | J13: =NETWORKDAYS(H13,I13,Holidays!$A$2:$A$40) -> 310
A15: Key milestones
A16: Milestone | B16: Tracker row | C16: Target date
A17: NDMA sign-off on proposal | B17: =ROW(Tracker!H5) -> 5 | C17: =Tracker!H5 -> 46310
A18: Pilot district selected | B18: =ROW(Tracker!H6) -> 6 | C18: =Tracker!H6 -> 46318
A19: Core agency feeds live (IMD, CWC) | B19: =ROW(Tracker!H25) -> 25 | C19: =Tracker!H25 -> 46359
A20: Flood forecast backtest passed | B20: =ROW(Tracker!H48) -> 48 | C20: =Tracker!H48 -> 46479
A21: Digital twin animates forecast | B21: =ROW(Tracker!H55) -> 55 | C21: =Tracker!H55 -> 46489
A22: Unified SEOC command screen | B22: =ROW(Tracker!H81) -> 81 | C22: =Tracker!H81 -> 46526
A23: End-to-end integration test | B23: =ROW(Tracker!H106) -> 106 | C23: =Tracker!H106 -> 46540
A24: UAT sign-off | B24: =ROW(Tracker!H108) -> 108 | C24: =Tracker!H108 -> 46568
A25: Shadow mode complete (monsoon 2027) | B25: =ROW(Tracker!H111) -> 111 | C25: =Tracker!H111 -> 46660
A26: Go / no-go for live use | B26: =ROW(Tracker!H112) -> 112 | C26: =Tracker!H112 -> 46667
A27: Phase 3 rollout plan approved | B27: =ROW(Tracker!H119) -> 119 | C27: =Tracker!H119 -> 46723

Sheet Decisions & Dependencies
A1: External Decisions & Dependencies
A2: Everything the team needs from NDMA or another agency. 'Needed by' = start of the first task that waits on it (linked to the Tracker).
A3: # | B3: Decision / dependency | C3: Owner | D3: Blocks | E3: Needed by | F3: Status | G3: Notes
A4: 1 | B4: Proposal walkthrough and sign-off | C4: NDMA | D4: Proposal walkthrough and sign-off with NDMA (P1) | E4: =Tracker!G5 -> 46307 | F4: Open
A5: 2 | B5: Nomination of candidate pilot districts | C5: NDMA / State SDMA | D5: Select Phase 1 pilot district (P2) | E5: =Tracker!G6 -> 46311 | F5: Open | G5: Prefer a well-mapped, flood-prone district (terrain-resolution risk).
A6: 3 | B6: Hosting / cloud approval (data residency in India) | C6: NDMA IT | D6: Hosting decision (MeghRaj / NIC / GovCloud) (H0) | E6: =Tracker!G95 -> 46311 | F6: Open | G6: Blocks all environments.
A7: 4 | B7: IMD data-sharing agreement | C7: IMD | D7: IMD data-sharing agreement (D1) | E7: =Tracker!G10 -> 46321 | F7: Open | G7: Formal agreements from day one (inter-agency risk).
A8: 5 | B8: CWC data-sharing agreement | C8: CWC | D8: CWC data-sharing agreement (D2) | E8: =Tracker!G11 -> 46321 | F8: Open
A9: 6 | B9: ISRO / NRSC imagery access | C9: NRSC | D9: ISRO / NRSC satellite data access (D3) | E9: =Tracker!G12 -> 46321 | F9: Open
A10: 7 | B10: Survey of India DEM licence | C10: Survey of India | D10: Survey of India high-resolution DEM licence (D4) | E10: =Tracker!G13 -> 46321 | F10: Open
A11: 8 | B11: Google Maps Platform budget | C11: NDMA Finance | D11: Google Maps Platform licence and billing (D6) | E11: =Tracker!G15 -> 46311 | F11: Open
A12: 9 | B12: Commercial imagery procurement | C12: NDMA Procurement | D12: Commercial high-resolution imagery procurement (D7) | E12: =Tracker!G16 -> 46321 | F12: Open | G12: Phase 1 pilot district only.
A13: 10 | B13: Privacy policy legal review (DPDP Act 2023) | C13: NDMA Legal | D13: Data governance and privacy policy (G1) | E13: =Tracker!G17 -> 46311 | F13: Open
A14: 11 | B14: IDRN inventory access | C14: NDMA / NIDM | D14: IDRN resource inventory import (I13) | E14: =Tracker!G32 -> 46346 | F14: Open
A15: 12 | B15: Pilot sensor feed access | C15: State water resources dept / vendor | D15: River / rain gauge sensor telemetry (pilot) (I14) | E15: =Tracker!G33 -> 46350 | F15: Open
A16: 13 | B16: WhatsApp Business API account | C16: NDMA | D16: WhatsApp ground-reporting bot (I17) | E16: =Tracker!G34 -> 46350 | F16: Open
A17: 14 | B17: NDRF / SDRF unit data and tracking feed | C17: NDRF / SDRF | D17: NDRF / SDRF unit and capability registry (F1); GPS / radio tracking integration (F2) | E17: =Tracker!G74 -> 46353 | F17: Open
A18: 15 | B18: SACHET / Cell Broadcast export format | C18: NDMA / C-DOT | D18: Export route and shelter plans for official channels (E14) | E18: =Tracker!G73 -> 46507 | F18: Open | G18: Operators issue messages; system never auto-sends.
A19: 16 | B19: Security auditor engagement | C19: NDMA IT | D19: Security audit (CERT-In empanelled auditor) (H4) | E19: =Tracker!G101 -> 46541 | F19: Open | G19: CERT-In empanelled.

Sheet Risks
A1: Risk Register
A2: Risks 1–5 from proposal section 7; 6–8 added for delivery. Impact / Likelihood are initial team estimates — review with NDMA.
A3: # | B3: Risk | C3: Impact | D3: Likelihood | E3: Mitigation | F3: Linked tasks | G3: Status
A4: 1 | B4: Terrain data resolution — inconsistent elevation data distorts hazard-flow predictions. | C4: High | D4: Medium | E4: Launch Phase 1 in a single well-mapped pilot district before scaling. | F4: P2, D4, I9 | G4: Open
A5: 2 | B5: Crowdsourced data reliability — misinformation or false reports corrupt the model. | C5: High | D5: High | E5: Strict NLP/verification filtering and trust scores before ingestion; operator review queue. | F5: I20, FB3, X5 | G5: Open
A6: 3 | B6: Model trust & validation — wrong predictions misdirect forces or plans. | C6: High | D6: Medium | E6: Backtest against historical data and run in shadow mode before live decisions. | F6: M11, T9, T10, V4, V5 | G6: Open
A7: 4 | B7: Data privacy & consent — citizen location and social data create legal liability. | C7: High | D7: Medium | E7: Data-governance and privacy policy built alongside the technical build; consent on every report. | F7: G1, G2, G3 | G7: Open
A8: 5 | B8: Inter-agency coordination — IMD, CWC, ISRO use siloed, incompatible formats. | C8: High | D8: High | E8: Formal data-sharing agreements and a common schema from day one. | F8: D1, D2, D3, I1 | G8: Open
A9: 6 | B9: Agreement delays push the schedule (agency approvals are outside team control). | C9: High | D9: High | E9: Start agreements immediately after pilot selection; build on open data (Copernicus, OSM) meanwhile. | F9: D1–D7, I8 | G9: Open
A10: 7 | B10: Shadow-mode window depends on monsoon timing; a quiet season gives few events. | C10: Medium | D10: Medium | E10: Supplement with historical replays; extend shadow mode or add a second pilot basin if needed. | F10: V4, T9 | G10: Open
A11: 8 | B11: System unavailable during a live disaster (surge load, outages). | C11: High | D11: Low | E11: Load testing at 3× peak, DR drill and low-bandwidth mode. | F11: H9, H10, U10 | G11: Open

Sheet Holidays
A1: Date | B1: Holiday | D1: Edit this list to match the NDMA gazetted holiday calendar; Working days on every tab uses A2:A40. The planned dates on the Tracker were scheduled with this list.
A2: 46315 | B2: Dussehra
A3: 46381 | B3: Christmas
A4: 46413 | B4: Republic Day
A5: 46472 | B5: Good Friday
